{
  "generated_at": "2026-02-28T18:53:57.328Z",
  "profiles": {
    "strict_simon": {
      "generated_at": "2026-02-28T18:53:57.159Z",
      "meta": {
        "total_candidates": 28,
        "evaluated_candidates": 28,
        "eligible_count": 14,
        "borderline_count": 1,
        "rejected_count": 14,
        "validation_error_count": 0
      },
      "top5": [
        {
          "rank": 1,
          "asset_id": "sui",
          "name": "Sui",
          "score": 66.8,
          "confidence": 76.83,
          "gate_status": "pass"
        },
        {
          "rank": 2,
          "asset_id": "chainlink",
          "name": "Chainlink",
          "score": 66.61,
          "confidence": 74.8,
          "gate_status": "pass"
        },
        {
          "rank": 3,
          "asset_id": "avalanche",
          "name": "Avalanche",
          "score": 62.22,
          "confidence": 71.45,
          "gate_status": "pass"
        },
        {
          "rank": 4,
          "asset_id": "uniswap",
          "name": "Uniswap",
          "score": 59.64,
          "confidence": 74.2,
          "gate_status": "pass"
        },
        {
          "rank": 5,
          "asset_id": "pepe",
          "name": "Pepe",
          "score": 57.08,
          "confidence": 74.35,
          "gate_status": "pass"
        }
      ]
    },
    "balanced": {
      "generated_at": "2026-02-28T18:53:57.223Z",
      "meta": {
        "total_candidates": 28,
        "evaluated_candidates": 28,
        "eligible_count": 18,
        "borderline_count": 2,
        "rejected_count": 10,
        "validation_error_count": 0
      },
      "top5": [
        {
          "rank": 1,
          "asset_id": "sui",
          "name": "Sui",
          "score": 68.05,
          "confidence": 76.83,
          "gate_status": "pass"
        },
        {
          "rank": 2,
          "asset_id": "chainlink",
          "name": "Chainlink",
          "score": 67.99,
          "confidence": 74.8,
          "gate_status": "pass"
        },
        {
          "rank": 3,
          "asset_id": "avalanche",
          "name": "Avalanche",
          "score": 63.77,
          "confidence": 71.45,
          "gate_status": "pass"
        },
        {
          "rank": 4,
          "asset_id": "uniswap",
          "name": "Uniswap",
          "score": 61.43,
          "confidence": 74.2,
          "gate_status": "pass"
        },
        {
          "rank": 5,
          "asset_id": "pepe",
          "name": "Pepe",
          "score": 59.09,
          "confidence": 74.35,
          "gate_status": "pass"
        }
      ]
    },
    "growth": {
      "generated_at": "2026-02-28T18:53:57.285Z",
      "meta": {
        "total_candidates": 28,
        "evaluated_candidates": 28,
        "eligible_count": 21,
        "borderline_count": 2,
        "rejected_count": 7,
        "validation_error_count": 0
      },
      "top5": [
        {
          "rank": 1,
          "asset_id": "chainlink",
          "name": "Chainlink",
          "score": 71.92,
          "confidence": 74.8,
          "gate_status": "pass"
        },
        {
          "rank": 2,
          "asset_id": "sui",
          "name": "Sui",
          "score": 71.06,
          "confidence": 76.83,
          "gate_status": "pass"
        },
        {
          "rank": 3,
          "asset_id": "avalanche",
          "name": "Avalanche",
          "score": 68.14,
          "confidence": 71.45,
          "gate_status": "pass"
        },
        {
          "rank": 4,
          "asset_id": "uniswap",
          "name": "Uniswap",
          "score": 66.41,
          "confidence": 74.2,
          "gate_status": "pass"
        },
        {
          "rank": 5,
          "asset_id": "pepe",
          "name": "Pepe",
          "score": 63.79,
          "confidence": 74.35,
          "gate_status": "pass"
        }
      ]
    }
  }
}
