{
  "generated_at": "2026-04-18T16:32:00.017Z",
  "meta": {
    "total_candidates": 28,
    "evaluated_candidates": 28,
    "eligible_count": 16,
    "borderline_count": 0,
    "rejected_count": 12,
    "validation_error_count": 0
  },
  "thresholds": {
    "min_mcap_usd": 40000000,
    "min_fdv_usd": 40000000,
    "min_est_liquidity_usd": 7000000,
    "min_tier1_cex_count": 1,
    "weights": {
      "market_strength": 0.35,
      "venue_liquidity": 0.3,
      "solana_demand": 0.25,
      "migration_feasibility": 0.1
    },
    "tier1_cex": [
      "Binance",
      "Coinbase",
      "OKX",
      "Bybit",
      "Kraken"
    ]
  },
  "calibration": {
    "profile": "strict_simon",
    "thresholds_used": {
      "min_mcap_usd": 40000000,
      "min_fdv_usd": 40000000,
      "min_est_liquidity_usd": 7000000,
      "min_tier1_cex_count": 1,
      "weights": {
        "market_strength": 0.35,
        "venue_liquidity": 0.3,
        "solana_demand": 0.25,
        "migration_feasibility": 0.1
      },
      "tier1_cex": [
        "Binance",
        "Coinbase",
        "OKX",
        "Bybit",
        "Kraken"
      ]
    },
    "counts": {
      "total": 28,
      "eligible": 16,
      "borderline": 0,
      "rejected": 12
    }
  },
  "eligible_ranked": [
    {
      "rank": 1,
      "asset_id": "chainlink",
      "name": "Chainlink",
      "symbol": "LINK",
      "origin_chain": "Ethereum",
      "gate_status": "pass",
      "readiness_score": 70.06,
      "adjusted_readiness_score": 66.44,
      "confidence_score": 74.18,
      "score_breakdown": {
        "market_strength": 66.03,
        "venue_liquidity": 56.33,
        "solana_demand": 85,
        "migration_feasibility": 88
      },
      "missing_data_flags": [],
      "explainability": {
        "weights": {
          "market_strength": 0.35,
          "venue_liquidity": 0.3,
          "solana_demand": 0.25,
          "migration_feasibility": 0.1
        },
        "inputs": {
          "mcap_usd": 6839634847,
          "fdv_usd": 9406732396,
          "est_liquidity_usd": 52342134,
          "tier1_cex_listings_count": 4,
          "demand_signal_score": 85,
          "migration_feasibility_score": 88
        }
      },
      "data_provenance": {
        "selected_sources": {
          "mcap_usd": "coingecko",
          "fdv_usd": "coingecko",
          "est_liquidity_usd": "coingecko",
          "tier1_cex_listings": "coingecko"
        },
        "conflicts": [
          {
            "field": "mcap_usd",
            "type": "numeric_divergence",
            "divergence_ratio": 0.638,
            "samples": [
              {
                "provider": "seed",
                "value": 11200000000
              },
              {
                "provider": "coingecko",
                "value": 6839634847
              }
            ]
          },
          {
            "field": "est_liquidity_usd",
            "type": "numeric_divergence",
            "divergence_ratio": 5.114,
            "samples": [
              {
                "provider": "seed",
                "value": 320000000
              },
              {
                "provider": "coingecko",
                "value": 52342134
              }
            ]
          }
        ],
        "provider_errors": []
      },
      "demand_evidence": {
        "mode": "proxy_weighted",
        "volume_score": 88,
        "social_velocity_score": 80,
        "solana_protocol_interest_score": 86,
        "evidence_links": [
          "https://www.coingecko.com/en/coins/chainlink"
        ]
      }
    },
    {
      "rank": 2,
      "asset_id": "sui",
      "name": "Sui",
      "symbol": "SUI",
      "origin_chain": "Sui",
      "gate_status": "pass",
      "readiness_score": 70.13,
      "adjusted_readiness_score": 66.39,
      "confidence_score": 73.35,
      "score_breakdown": {
        "market_strength": 62.49,
        "venue_liquidity": 66.38,
        "solana_demand": 81.4,
        "migration_feasibility": 80
      },
      "missing_data_flags": [
        "missing_origin_token_address"
      ],
      "explainability": {
        "weights": {
          "market_strength": 0.35,
          "venue_liquidity": 0.3,
          "solana_demand": 0.25,
          "migration_feasibility": 0.1
        },
        "inputs": {
          "mcap_usd": 3823625333,
          "fdv_usd": 9671766169,
          "est_liquidity_usd": 62030213.25,
          "tier1_cex_listings_count": 5,
          "demand_signal_score": 81.4,
          "migration_feasibility_score": 80
        }
      },
      "data_provenance": {
        "selected_sources": {
          "mcap_usd": "coingecko",
          "fdv_usd": "coingecko",
          "est_liquidity_usd": "coingecko",
          "tier1_cex_listings": "seed"
        },
        "conflicts": [
          {
            "field": "mcap_usd",
            "type": "numeric_divergence",
            "divergence_ratio": 0.595,
            "samples": [
              {
                "provider": "seed",
                "value": 6100000000
              },
              {
                "provider": "coingecko",
                "value": 3823625333
              }
            ]
          },
          {
            "field": "fdv_usd",
            "type": "numeric_divergence",
            "divergence_ratio": 0.758,
            "samples": [
              {
                "provider": "seed",
                "value": 17000000000
              },
              {
                "provider": "coingecko",
                "value": 9671766169
              }
            ]
          },
          {
            "field": "est_liquidity_usd",
            "type": "numeric_divergence",
            "divergence_ratio": 3.03,
            "samples": [
              {
                "provider": "seed",
                "value": 250000000
              },
              {
                "provider": "coingecko",
                "value": 62030213.25
              }
            ]
          }
        ],
        "provider_errors": []
      },
      "demand_evidence": {
        "mode": "proxy_weighted",
        "volume_score": 82,
        "social_velocity_score": 83,
        "solana_protocol_interest_score": 79,
        "evidence_links": [
          "https://www.coingecko.com/en/coins/sui"
        ]
      }
    },
    {
      "rank": 3,
      "asset_id": "avalanche",
      "name": "Avalanche",
      "symbol": "AVAX",
      "origin_chain": "Avalanche",
      "gate_status": "pass",
      "readiness_score": 67.98,
      "adjusted_readiness_score": 63.79,
      "confidence_score": 69.22,
      "score_breakdown": {
        "market_strength": 58.05,
        "venue_liquidity": 62.03,
        "solana_demand": 80.6,
        "migration_feasibility": 89
      },
      "missing_data_flags": [
        "missing_origin_token_address"
      ],
      "explainability": {
        "weights": {
          "market_strength": 0.35,
          "venue_liquidity": 0.3,
          "solana_demand": 0.25,
          "migration_feasibility": 0.1
        },
        "inputs": {
          "mcap_usd": 4069677724,
          "fdv_usd": 4368175641,
          "est_liquidity_usd": 43290970.8,
          "tier1_cex_listings_count": 5,
          "demand_signal_score": 80.6,
          "migration_feasibility_score": 89
        }
      },
      "data_provenance": {
        "selected_sources": {
          "mcap_usd": "coingecko",
          "fdv_usd": "coingecko",
          "est_liquidity_usd": "coingecko",
          "tier1_cex_listings": "seed"
        },
        "conflicts": [
          {
            "field": "mcap_usd",
            "type": "numeric_divergence",
            "divergence_ratio": 2.686,
            "samples": [
              {
                "provider": "seed",
                "value": 15000000000
              },
              {
                "provider": "coingecko",
                "value": 4069677724
              }
            ]
          },
          {
            "field": "fdv_usd",
            "type": "numeric_divergence",
            "divergence_ratio": 2.892,
            "samples": [
              {
                "provider": "seed",
                "value": 17000000000
              },
              {
                "provider": "coingecko",
                "value": 4368175641
              }
            ]
          },
          {
            "field": "est_liquidity_usd",
            "type": "numeric_divergence",
            "divergence_ratio": 9.626,
            "samples": [
              {
                "provider": "seed",
                "value": 460000000
              },
              {
                "provider": "coingecko",
                "value": 43290970.8
              }
            ]
          }
        ],
        "provider_errors": []
      },
      "demand_evidence": {
        "mode": "proxy_weighted",
        "volume_score": 86,
        "social_velocity_score": 74,
        "solana_protocol_interest_score": 80,
        "evidence_links": [
          "https://www.coingecko.com/en/coins/avalanche"
        ]
      }
    },
    {
      "rank": 4,
      "asset_id": "pepe",
      "name": "Pepe",
      "symbol": "PEPE",
      "origin_chain": "Ethereum",
      "gate_status": "pass",
      "readiness_score": 63.75,
      "adjusted_readiness_score": 60.33,
      "confidence_score": 73.18,
      "score_breakdown": {
        "market_strength": 46.03,
        "venue_liquidity": 66.38,
        "solana_demand": 84.9,
        "migration_feasibility": 65
      },
      "missing_data_flags": [],
      "explainability": {
        "weights": {
          "market_strength": 0.35,
          "venue_liquidity": 0.3,
          "solana_demand": 0.25,
          "migration_feasibility": 0.1
        },
        "inputs": {
          "mcap_usd": 1605497385,
          "fdv_usd": 1605497385,
          "est_liquidity_usd": 62000985.599999994,
          "tier1_cex_listings_count": 5,
          "demand_signal_score": 84.9,
          "migration_feasibility_score": 65
        }
      },
      "data_provenance": {
        "selected_sources": {
          "mcap_usd": "coingecko",
          "fdv_usd": "coingecko",
          "est_liquidity_usd": "coingecko",
          "tier1_cex_listings": "seed"
        },
        "conflicts": [
          {
            "field": "mcap_usd",
            "type": "numeric_divergence",
            "divergence_ratio": 1.305,
            "samples": [
              {
                "provider": "seed",
                "value": 3700000000
              },
              {
                "provider": "coingecko",
                "value": 1605497385
              }
            ]
          },
          {
            "field": "fdv_usd",
            "type": "numeric_divergence",
            "divergence_ratio": 1.305,
            "samples": [
              {
                "provider": "seed",
                "value": 3700000000
              },
              {
                "provider": "coingecko",
                "value": 1605497385
              }
            ]
          },
          {
            "field": "est_liquidity_usd",
            "type": "numeric_divergence",
            "divergence_ratio": 2.226,
            "samples": [
              {
                "provider": "seed",
                "value": 200000000
              },
              {
                "provider": "coingecko",
                "value": 62000985.599999994
              }
            ]
          }
        ],
        "provider_errors": []
      },
      "demand_evidence": {
        "mode": "proxy_weighted",
        "volume_score": 90,
        "social_velocity_score": 93,
        "solana_protocol_interest_score": 70,
        "evidence_links": [
          "https://www.coingecko.com/en/coins/pepe"
        ]
      }
    },
    {
      "rank": 5,
      "asset_id": "uniswap",
      "name": "Uniswap",
      "symbol": "UNI",
      "origin_chain": "Ethereum",
      "gate_status": "pass",
      "readiness_score": 61.64,
      "adjusted_readiness_score": 58.37,
      "confidence_score": 73.44,
      "score_breakdown": {
        "market_strength": 51.77,
        "venue_liquidity": 48.73,
        "solana_demand": 81.6,
        "migration_feasibility": 85
      },
      "missing_data_flags": [],
      "explainability": {
        "weights": {
          "market_strength": 0.35,
          "venue_liquidity": 0.3,
          "solana_demand": 0.25,
          "migration_feasibility": 0.1
        },
        "inputs": {
          "mcap_usd": 2148020951,
          "fdv_usd": 3040421843,
          "est_liquidity_usd": 27924208.2,
          "tier1_cex_listings_count": 4,
          "demand_signal_score": 81.6,
          "migration_feasibility_score": 85
        }
      },
      "data_provenance": {
        "selected_sources": {
          "mcap_usd": "coingecko",
          "fdv_usd": "coingecko",
          "est_liquidity_usd": "coingecko",
          "tier1_cex_listings": "coingecko"
        },
        "conflicts": [
          {
            "field": "mcap_usd",
            "type": "numeric_divergence",
            "divergence_ratio": 1.607,
            "samples": [
              {
                "provider": "seed",
                "value": 5600000000
              },
              {
                "provider": "coingecko",
                "value": 2148020951
              }
            ]
          },
          {
            "field": "fdv_usd",
            "type": "numeric_divergence",
            "divergence_ratio": 1.006,
            "samples": [
              {
                "provider": "seed",
                "value": 6100000000
              },
              {
                "provider": "coingecko",
                "value": 3040421843
              }
            ]
          },
          {
            "field": "est_liquidity_usd",
            "type": "numeric_divergence",
            "divergence_ratio": 5.446,
            "samples": [
              {
                "provider": "seed",
                "value": 180000000
              },
              {
                "provider": "coingecko",
                "value": 27924208.2
              }
            ]
          }
        ],
        "provider_errors": []
      },
      "demand_evidence": {
        "mode": "proxy_weighted",
        "volume_score": 84,
        "social_velocity_score": 78,
        "solana_protocol_interest_score": 82,
        "evidence_links": [
          "https://www.coingecko.com/en/coins/uniswap"
        ]
      }
    },
    {
      "rank": 6,
      "asset_id": "aave",
      "name": "Aave",
      "symbol": "AAVE",
      "origin_chain": "Ethereum",
      "gate_status": "pass",
      "readiness_score": 59.84,
      "adjusted_readiness_score": 57.11,
      "confidence_score": 77.15,
      "score_breakdown": {
        "market_strength": 47.15,
        "venue_liquidity": 54.64,
        "solana_demand": 75,
        "migration_feasibility": 82
      },
      "missing_data_flags": [],
      "explainability": {
        "weights": {
          "market_strength": 0.35,
          "venue_liquidity": 0.3,
          "solana_demand": 0.25,
          "migration_feasibility": 0.1
        },
        "inputs": {
          "mcap_usd": 1710717725,
          "fdv_usd": 1804789379,
          "est_liquidity_usd": 45527549.1,
          "tier1_cex_listings_count": 4,
          "demand_signal_score": 75,
          "migration_feasibility_score": 82
        }
      },
      "data_provenance": {
        "selected_sources": {
          "mcap_usd": "coingecko",
          "fdv_usd": "coingecko",
          "est_liquidity_usd": "coingecko",
          "tier1_cex_listings": "coingecko"
        },
        "conflicts": [
          {
            "field": "mcap_usd",
            "type": "numeric_divergence",
            "divergence_ratio": 0.52,
            "samples": [
              {
                "provider": "seed",
                "value": 2600000000
              },
              {
                "provider": "coingecko",
                "value": 1710717725
              }
            ]
          },
          {
            "field": "fdv_usd",
            "type": "numeric_divergence",
            "divergence_ratio": 0.607,
            "samples": [
              {
                "provider": "seed",
                "value": 2900000000
              },
              {
                "provider": "coingecko",
                "value": 1804789379
              }
            ]
          },
          {
            "field": "est_liquidity_usd",
            "type": "numeric_divergence",
            "divergence_ratio": 0.977,
            "samples": [
              {
                "provider": "seed",
                "value": 90000000
              },
              {
                "provider": "coingecko",
                "value": 45527549.1
              }
            ]
          }
        ],
        "provider_errors": []
      },
      "demand_evidence": {
        "mode": "fallback_seed_score",
        "evidence_links": []
      }
    },
    {
      "rank": 7,
      "asset_id": "near",
      "name": "NEAR",
      "symbol": "NEAR",
      "origin_chain": "Near",
      "gate_status": "pass",
      "readiness_score": 60.42,
      "adjusted_readiness_score": 56.85,
      "confidence_score": 70.47,
      "score_breakdown": {
        "market_strength": 47.35,
        "venue_liquidity": 58.08,
        "solana_demand": 72.9,
        "migration_feasibility": 82
      },
      "missing_data_flags": [
        "missing_origin_token_address"
      ],
      "explainability": {
        "weights": {
          "market_strength": 0.35,
          "venue_liquidity": 0.3,
          "solana_demand": 0.25,
          "migration_feasibility": 0.1
        },
        "inputs": {
          "mcap_usd": 1784744117,
          "fdv_usd": 1784744151,
          "est_liquidity_usd": 31220513.849999998,
          "tier1_cex_listings_count": 5,
          "demand_signal_score": 72.9,
          "migration_feasibility_score": 82
        }
      },
      "data_provenance": {
        "selected_sources": {
          "mcap_usd": "coingecko",
          "fdv_usd": "coingecko",
          "est_liquidity_usd": "coingecko",
          "tier1_cex_listings": "seed"
        },
        "conflicts": [
          {
            "field": "mcap_usd",
            "type": "numeric_divergence",
            "divergence_ratio": 2.418,
            "samples": [
              {
                "provider": "seed",
                "value": 6100000000
              },
              {
                "provider": "coingecko",
                "value": 1784744117
              }
            ]
          },
          {
            "field": "fdv_usd",
            "type": "numeric_divergence",
            "divergence_ratio": 2.642,
            "samples": [
              {
                "provider": "seed",
                "value": 6500000000
              },
              {
                "provider": "coingecko",
                "value": 1784744151
              }
            ]
          },
          {
            "field": "est_liquidity_usd",
            "type": "numeric_divergence",
            "divergence_ratio": 5.726,
            "samples": [
              {
                "provider": "seed",
                "value": 210000000
              },
              {
                "provider": "coingecko",
                "value": 31220513.849999998
              }
            ]
          }
        ],
        "provider_errors": []
      },
      "demand_evidence": {
        "mode": "proxy_weighted",
        "volume_score": 75,
        "social_velocity_score": 70,
        "solana_protocol_interest_score": 73,
        "evidence_links": [
          "https://www.coingecko.com/en/coins/near"
        ]
      }
    },
    {
      "rank": 8,
      "asset_id": "ethena",
      "name": "Ethena",
      "symbol": "ENA",
      "origin_chain": "Ethereum",
      "gate_status": "pass",
      "readiness_score": 56.95,
      "adjusted_readiness_score": 52.35,
      "confidence_score": 59.6,
      "score_breakdown": {
        "market_strength": 44.32,
        "venue_liquidity": 45.14,
        "solana_demand": 80,
        "migration_feasibility": 79
      },
      "missing_data_flags": [
        "low_data_confidence"
      ],
      "explainability": {
        "weights": {
          "market_strength": 0.35,
          "venue_liquidity": 0.3,
          "solana_demand": 0.25,
          "migration_feasibility": 0.1
        },
        "inputs": {
          "mcap_usd": 1077054425,
          "fdv_usd": 1844402868,
          "est_liquidity_usd": 40212124.949999996,
          "tier1_cex_listings_count": 3,
          "demand_signal_score": 80,
          "migration_feasibility_score": 79
        }
      },
      "data_provenance": {
        "selected_sources": {
          "mcap_usd": "coingecko",
          "fdv_usd": "coingecko",
          "est_liquidity_usd": "coingecko",
          "tier1_cex_listings": "seed"
        },
        "conflicts": [
          {
            "field": "mcap_usd",
            "type": "numeric_divergence",
            "divergence_ratio": 0.671,
            "samples": [
              {
                "provider": "seed",
                "value": 1800000000
              },
              {
                "provider": "coingecko",
                "value": 1077054425
              }
            ]
          },
          {
            "field": "fdv_usd",
            "type": "numeric_divergence",
            "divergence_ratio": 2.036,
            "samples": [
              {
                "provider": "seed",
                "value": 5600000000
              },
              {
                "provider": "coingecko",
                "value": 1844402868
              }
            ]
          },
          {
            "field": "est_liquidity_usd",
            "type": "numeric_divergence",
            "divergence_ratio": 1.114,
            "samples": [
              {
                "provider": "seed",
                "value": 85000000
              },
              {
                "provider": "coingecko",
                "value": 40212124.949999996
              }
            ]
          }
        ],
        "provider_errors": [
          {
            "provider": "coingecko",
            "error": "http_429"
          }
        ]
      },
      "demand_evidence": {
        "mode": "fallback_seed_score",
        "evidence_links": []
      }
    },
    {
      "rank": 9,
      "asset_id": "aptos",
      "name": "Aptos",
      "symbol": "APT",
      "origin_chain": "Aptos",
      "gate_status": "pass",
      "readiness_score": 55.74,
      "adjusted_readiness_score": 52.09,
      "confidence_score": 67.3,
      "score_breakdown": {
        "market_strength": 39.17,
        "venue_liquidity": 49.2,
        "solana_demand": 77.5,
        "migration_feasibility": 79
      },
      "missing_data_flags": [
        "missing_origin_token_address"
      ],
      "explainability": {
        "weights": {
          "market_strength": 0.35,
          "venue_liquidity": 0.3,
          "solana_demand": 0.25,
          "migration_feasibility": 0.1
        },
        "inputs": {
          "mcap_usd": 762725724,
          "fdv_usd": 1136320716,
          "est_liquidity_usd": 14977310.7,
          "tier1_cex_listings_count": 5,
          "demand_signal_score": 77.5,
          "migration_feasibility_score": 79
        }
      },
      "data_provenance": {
        "selected_sources": {
          "mcap_usd": "coingecko",
          "fdv_usd": "coingecko",
          "est_liquidity_usd": "coingecko",
          "tier1_cex_listings": "seed"
        },
        "conflicts": [
          {
            "field": "mcap_usd",
            "type": "numeric_divergence",
            "divergence_ratio": 8.047,
            "samples": [
              {
                "provider": "seed",
                "value": 6900000000
              },
              {
                "provider": "coingecko",
                "value": 762725724
              }
            ]
          },
          {
            "field": "fdv_usd",
            "type": "numeric_divergence",
            "divergence_ratio": 7.624,
            "samples": [
              {
                "provider": "seed",
                "value": 9800000000
              },
              {
                "provider": "coingecko",
                "value": 1136320716
              }
            ]
          },
          {
            "field": "est_liquidity_usd",
            "type": "numeric_divergence",
            "divergence_ratio": 11.686,
            "samples": [
              {
                "provider": "seed",
                "value": 190000000
              },
              {
                "provider": "coingecko",
                "value": 14977310.7
              }
            ]
          }
        ],
        "provider_errors": []
      },
      "demand_evidence": {
        "mode": "proxy_weighted",
        "volume_score": 79,
        "social_velocity_score": 76,
        "solana_protocol_interest_score": 77,
        "evidence_links": [
          "https://www.coingecko.com/en/coins/aptos"
        ]
      }
    },
    {
      "rank": 10,
      "asset_id": "worldcoin",
      "name": "Worldcoin",
      "symbol": "WLD",
      "origin_chain": "Optimism",
      "gate_status": "pass",
      "readiness_score": 54.1,
      "adjusted_readiness_score": 51.11,
      "confidence_score": 72.36,
      "score_breakdown": {
        "market_strength": 45.52,
        "venue_liquidity": 43.39,
        "solana_demand": 71,
        "migration_feasibility": 74
      },
      "missing_data_flags": [],
      "explainability": {
        "weights": {
          "market_strength": 0.35,
          "venue_liquidity": 0.3,
          "solana_demand": 0.25,
          "migration_feasibility": 0.1
        },
        "inputs": {
          "mcap_usd": 895701631,
          "fdv_usd": 2729542667,
          "est_liquidity_usd": 34805692.05,
          "tier1_cex_listings_count": 3,
          "demand_signal_score": 71,
          "migration_feasibility_score": 74
        }
      },
      "data_provenance": {
        "selected_sources": {
          "mcap_usd": "coingecko",
          "fdv_usd": "coingecko",
          "est_liquidity_usd": "coingecko",
          "tier1_cex_listings": "seed"
        },
        "conflicts": [
          {
            "field": "mcap_usd",
            "type": "numeric_divergence",
            "divergence_ratio": 1.01,
            "samples": [
              {
                "provider": "seed",
                "value": 1800000000
              },
              {
                "provider": "coingecko",
                "value": 895701631
              }
            ]
          },
          {
            "field": "fdv_usd",
            "type": "numeric_divergence",
            "divergence_ratio": 3.396,
            "samples": [
              {
                "provider": "seed",
                "value": 12000000000
              },
              {
                "provider": "coingecko",
                "value": 2729542667
              }
            ]
          },
          {
            "field": "est_liquidity_usd",
            "type": "numeric_divergence",
            "divergence_ratio": 1.816,
            "samples": [
              {
                "provider": "seed",
                "value": 98000000
              },
              {
                "provider": "coingecko",
                "value": 34805692.05
              }
            ]
          }
        ],
        "provider_errors": []
      },
      "demand_evidence": {
        "mode": "fallback_seed_score",
        "evidence_links": []
      }
    },
    {
      "rank": 11,
      "asset_id": "arbitrum",
      "name": "Arbitrum",
      "symbol": "ARB",
      "origin_chain": "Arbitrum",
      "gate_status": "pass",
      "readiness_score": 54.17,
      "adjusted_readiness_score": 50.9,
      "confidence_score": 69.82,
      "score_breakdown": {
        "market_strength": 40.05,
        "venue_liquidity": 41.94,
        "solana_demand": 75.5,
        "migration_feasibility": 87
      },
      "missing_data_flags": [],
      "explainability": {
        "weights": {
          "market_strength": 0.35,
          "venue_liquidity": 0.3,
          "solana_demand": 0.25,
          "migration_feasibility": 0.1
        },
        "inputs": {
          "mcap_usd": 777230979,
          "fdv_usd": 1286630698,
          "est_liquidity_usd": 15923917.35,
          "tier1_cex_listings_count": 4,
          "demand_signal_score": 75.5,
          "migration_feasibility_score": 87
        }
      },
      "data_provenance": {
        "selected_sources": {
          "mcap_usd": "coingecko",
          "fdv_usd": "coingecko",
          "est_liquidity_usd": "coingecko",
          "tier1_cex_listings": "seed"
        },
        "conflicts": [
          {
            "field": "mcap_usd",
            "type": "numeric_divergence",
            "divergence_ratio": 3.503,
            "samples": [
              {
                "provider": "seed",
                "value": 3500000000
              },
              {
                "provider": "coingecko",
                "value": 777230979
              }
            ]
          },
          {
            "field": "fdv_usd",
            "type": "numeric_divergence",
            "divergence_ratio": 3.741,
            "samples": [
              {
                "provider": "seed",
                "value": 6100000000
              },
              {
                "provider": "coingecko",
                "value": 1286630698
              }
            ]
          },
          {
            "field": "est_liquidity_usd",
            "type": "numeric_divergence",
            "divergence_ratio": 5.908,
            "samples": [
              {
                "provider": "seed",
                "value": 110000000
              },
              {
                "provider": "coingecko",
                "value": 15923917.35
              }
            ]
          }
        ],
        "provider_errors": []
      },
      "demand_evidence": {
        "mode": "proxy_weighted",
        "volume_score": 77,
        "social_velocity_score": 74,
        "solana_protocol_interest_score": 75,
        "evidence_links": [
          "https://www.coingecko.com/en/coins/arbitrum"
        ]
      }
    },
    {
      "rank": 12,
      "asset_id": "optimism",
      "name": "Optimism",
      "symbol": "OP",
      "origin_chain": "Optimism",
      "gate_status": "pass",
      "readiness_score": 47.96,
      "adjusted_readiness_score": 44.78,
      "confidence_score": 66.83,
      "score_breakdown": {
        "market_strength": 28.25,
        "venue_liquidity": 35.49,
        "solana_demand": 74.5,
        "migration_feasibility": 88
      },
      "missing_data_flags": [],
      "explainability": {
        "weights": {
          "market_strength": 0.35,
          "venue_liquidity": 0.3,
          "solana_demand": 0.25,
          "migration_feasibility": 0.1
        },
        "inputs": {
          "mcap_usd": 274077583,
          "fdv_usd": 552651971,
          "est_liquidity_usd": 9342495.9,
          "tier1_cex_listings_count": 4,
          "demand_signal_score": 74.5,
          "migration_feasibility_score": 88
        }
      },
      "data_provenance": {
        "selected_sources": {
          "mcap_usd": "coingecko",
          "fdv_usd": "coingecko",
          "est_liquidity_usd": "coingecko",
          "tier1_cex_listings": "seed"
        },
        "conflicts": [
          {
            "field": "mcap_usd",
            "type": "numeric_divergence",
            "divergence_ratio": 9.946,
            "samples": [
              {
                "provider": "seed",
                "value": 3000000000
              },
              {
                "provider": "coingecko",
                "value": 274077583
              }
            ]
          },
          {
            "field": "fdv_usd",
            "type": "numeric_divergence",
            "divergence_ratio": 15.828,
            "samples": [
              {
                "provider": "seed",
                "value": 9300000000
              },
              {
                "provider": "coingecko",
                "value": 552651971
              }
            ]
          },
          {
            "field": "est_liquidity_usd",
            "type": "numeric_divergence",
            "divergence_ratio": 12.38,
            "samples": [
              {
                "provider": "seed",
                "value": 125000000
              },
              {
                "provider": "coingecko",
                "value": 9342495.9
              }
            ]
          }
        ],
        "provider_errors": []
      },
      "demand_evidence": {
        "mode": "proxy_weighted",
        "volume_score": 76,
        "social_velocity_score": 73,
        "solana_protocol_interest_score": 74,
        "evidence_links": [
          "https://www.coingecko.com/en/coins/optimism"
        ]
      }
    },
    {
      "rank": 13,
      "asset_id": "pendle",
      "name": "Pendle",
      "symbol": "PENDLE",
      "origin_chain": "Ethereum",
      "gate_status": "pass",
      "readiness_score": 45.1,
      "adjusted_readiness_score": 42.91,
      "confidence_score": 75.72,
      "score_breakdown": {
        "market_strength": 25.05,
        "venue_liquidity": 38.78,
        "solana_demand": 70,
        "migration_feasibility": 72
      },
      "missing_data_flags": [],
      "explainability": {
        "weights": {
          "market_strength": 0.35,
          "venue_liquidity": 0.3,
          "solana_demand": 0.25,
          "migration_feasibility": 0.1
        },
        "inputs": {
          "mcap_usd": 231199466,
          "fdv_usd": 390065248,
          "est_liquidity_usd": 12267264,
          "tier1_cex_listings_count": 4,
          "demand_signal_score": 70,
          "migration_feasibility_score": 72
        }
      },
      "data_provenance": {
        "selected_sources": {
          "mcap_usd": "coingecko",
          "fdv_usd": "coingecko",
          "est_liquidity_usd": "coingecko",
          "tier1_cex_listings": "coingecko"
        },
        "conflicts": [
          {
            "field": "mcap_usd",
            "type": "numeric_divergence",
            "divergence_ratio": 1.811,
            "samples": [
              {
                "provider": "seed",
                "value": 650000000
              },
              {
                "provider": "coingecko",
                "value": 231199466
              }
            ]
          },
          {
            "field": "fdv_usd",
            "type": "numeric_divergence",
            "divergence_ratio": 0.923,
            "samples": [
              {
                "provider": "seed",
                "value": 750000000
              },
              {
                "provider": "coingecko",
                "value": 390065248
              }
            ]
          },
          {
            "field": "est_liquidity_usd",
            "type": "numeric_divergence",
            "divergence_ratio": 1.119,
            "samples": [
              {
                "provider": "seed",
                "value": 26000000
              },
              {
                "provider": "coingecko",
                "value": 12267264
              }
            ]
          }
        ],
        "provider_errors": []
      },
      "demand_evidence": {
        "mode": "fallback_seed_score",
        "evidence_links": []
      }
    },
    {
      "rank": 14,
      "asset_id": "curve",
      "name": "Curve DAO",
      "symbol": "CRV",
      "origin_chain": "Ethereum",
      "gate_status": "pass",
      "readiness_score": 44.9,
      "adjusted_readiness_score": 42.65,
      "confidence_score": 74.97,
      "score_breakdown": {
        "market_strength": 29.87,
        "venue_liquidity": 36.3,
        "solana_demand": 65,
        "migration_feasibility": 73
      },
      "missing_data_flags": [],
      "explainability": {
        "weights": {
          "market_strength": 0.35,
          "venue_liquidity": 0.3,
          "solana_demand": 0.25,
          "migration_feasibility": 0.1
        },
        "inputs": {
          "mcap_usd": 351342992,
          "fdv_usd": 555682769,
          "est_liquidity_usd": 9991032.299999999,
          "tier1_cex_listings_count": 4,
          "demand_signal_score": 65,
          "migration_feasibility_score": 73
        }
      },
      "data_provenance": {
        "selected_sources": {
          "mcap_usd": "coingecko",
          "fdv_usd": "coingecko",
          "est_liquidity_usd": "coingecko",
          "tier1_cex_listings": "coingecko"
        },
        "conflicts": [
          {
            "field": "mcap_usd",
            "type": "numeric_divergence",
            "divergence_ratio": 1.675,
            "samples": [
              {
                "provider": "seed",
                "value": 940000000
              },
              {
                "provider": "coingecko",
                "value": 351342992
              }
            ]
          },
          {
            "field": "fdv_usd",
            "type": "numeric_divergence",
            "divergence_ratio": 1.249,
            "samples": [
              {
                "provider": "seed",
                "value": 1250000000
              },
              {
                "provider": "coingecko",
                "value": 555682769
              }
            ]
          },
          {
            "field": "est_liquidity_usd",
            "type": "numeric_divergence",
            "divergence_ratio": 2.203,
            "samples": [
              {
                "provider": "seed",
                "value": 32000000
              },
              {
                "provider": "coingecko",
                "value": 9991032.299999999
              }
            ]
          }
        ],
        "provider_errors": []
      },
      "demand_evidence": {
        "mode": "fallback_seed_score",
        "evidence_links": []
      }
    },
    {
      "rank": 15,
      "asset_id": "celestia",
      "name": "Celestia",
      "symbol": "TIA",
      "origin_chain": "Osmosis",
      "gate_status": "pass",
      "readiness_score": 44.65,
      "adjusted_readiness_score": 41.86,
      "confidence_score": 68.82,
      "score_breakdown": {
        "market_strength": 29.07,
        "venue_liquidity": 32.6,
        "solana_demand": 72,
        "migration_feasibility": 67
      },
      "missing_data_flags": [
        "missing_origin_token_address"
      ],
      "explainability": {
        "weights": {
          "market_strength": 0.35,
          "venue_liquidity": 0.3,
          "solana_demand": 0.25,
          "migration_feasibility": 0.1
        },
        "inputs": {
          "mcap_usd": 364258164,
          "fdv_usd": 468826241,
          "est_liquidity_usd": 14253007.35,
          "tier1_cex_listings_count": 3,
          "demand_signal_score": 72,
          "migration_feasibility_score": 67
        }
      },
      "data_provenance": {
        "selected_sources": {
          "mcap_usd": "coingecko",
          "fdv_usd": "coingecko",
          "est_liquidity_usd": "coingecko",
          "tier1_cex_listings": "seed"
        },
        "conflicts": [
          {
            "field": "mcap_usd",
            "type": "numeric_divergence",
            "divergence_ratio": 3.392,
            "samples": [
              {
                "provider": "seed",
                "value": 1600000000
              },
              {
                "provider": "coingecko",
                "value": 364258164
              }
            ]
          },
          {
            "field": "fdv_usd",
            "type": "numeric_divergence",
            "divergence_ratio": 10.092,
            "samples": [
              {
                "provider": "seed",
                "value": 5200000000
              },
              {
                "provider": "coingecko",
                "value": 468826241
              }
            ]
          },
          {
            "field": "est_liquidity_usd",
            "type": "numeric_divergence",
            "divergence_ratio": 3.35,
            "samples": [
              {
                "provider": "seed",
                "value": 62000000
              },
              {
                "provider": "coingecko",
                "value": 14253007.35
              }
            ]
          }
        ],
        "provider_errors": []
      },
      "demand_evidence": {
        "mode": "fallback_seed_score",
        "evidence_links": []
      }
    },
    {
      "rank": 16,
      "asset_id": "compound",
      "name": "Compound",
      "symbol": "COMP",
      "origin_chain": "Ethereum",
      "gate_status": "pass",
      "readiness_score": 41.17,
      "adjusted_readiness_score": 39.19,
      "confidence_score": 75.9,
      "score_breakdown": {
        "market_strength": 23.19,
        "venue_liquidity": 37.51,
        "solana_demand": 60,
        "migration_feasibility": 68
      },
      "missing_data_flags": [],
      "explainability": {
        "weights": {
          "market_strength": 0.35,
          "venue_liquidity": 0.3,
          "solana_demand": 0.25,
          "migration_feasibility": 0.1
        },
        "inputs": {
          "mcap_usd": 252805256,
          "fdv_usd": 261481492,
          "est_liquidity_usd": 11040640.65,
          "tier1_cex_listings_count": 4,
          "demand_signal_score": 60,
          "migration_feasibility_score": 68
        }
      },
      "data_provenance": {
        "selected_sources": {
          "mcap_usd": "coingecko",
          "fdv_usd": "coingecko",
          "est_liquidity_usd": "coingecko",
          "tier1_cex_listings": "coingecko"
        },
        "conflicts": [
          {
            "field": "mcap_usd",
            "type": "numeric_divergence",
            "divergence_ratio": 1.452,
            "samples": [
              {
                "provider": "seed",
                "value": 620000000
              },
              {
                "provider": "coingecko",
                "value": 252805256
              }
            ]
          },
          {
            "field": "fdv_usd",
            "type": "numeric_divergence",
            "divergence_ratio": 1.639,
            "samples": [
              {
                "provider": "seed",
                "value": 690000000
              },
              {
                "provider": "coingecko",
                "value": 261481492
              }
            ]
          },
          {
            "field": "est_liquidity_usd",
            "type": "numeric_divergence",
            "divergence_ratio": 0.63,
            "samples": [
              {
                "provider": "seed",
                "value": 18000000
              },
              {
                "provider": "coingecko",
                "value": 11040640.65
              }
            ]
          }
        ],
        "provider_errors": []
      },
      "demand_evidence": {
        "mode": "fallback_seed_score",
        "evidence_links": []
      }
    }
  ],
  "rejected": [
    {
      "asset_id": "maker",
      "name": "Maker",
      "symbol": "MKR",
      "origin_chain": "Ethereum",
      "rejection_reasons": [
        "insufficient_estimated_liquidity"
      ],
      "data_conflicts": [
        {
          "field": "fdv_usd",
          "type": "numeric_divergence",
          "divergence_ratio": 8.666,
          "samples": [
            {
              "provider": "seed",
              "value": 1600000000
            },
            {
              "provider": "coingecko",
              "value": 165520312
            }
          ]
        },
        {
          "field": "est_liquidity_usd",
          "type": "numeric_divergence",
          "divergence_ratio": 5542.729,
          "samples": [
            {
              "provider": "seed",
              "value": 50000000
            },
            {
              "provider": "coingecko",
              "value": 9019.199999999999
            }
          ]
        }
      ]
    },
    {
      "asset_id": "base-ecosystem-proxy",
      "name": "Aerodrome",
      "symbol": "AERO",
      "origin_chain": "Base",
      "rejection_reasons": [
        "insufficient_estimated_liquidity"
      ],
      "data_conflicts": [
        {
          "field": "est_liquidity_usd",
          "type": "numeric_divergence",
          "divergence_ratio": 2.174,
          "samples": [
            {
              "provider": "seed",
              "value": 12000000
            },
            {
              "provider": "coingecko",
              "value": 3780544.5
            }
          ]
        }
      ]
    },
    {
      "asset_id": "polygon",
      "name": "Polygon",
      "symbol": "POL",
      "origin_chain": "Polygon",
      "rejection_reasons": [
        "insufficient_estimated_liquidity"
      ],
      "data_conflicts": [
        {
          "field": "fdv_usd",
          "type": "numeric_divergence",
          "divergence_ratio": 3.052,
          "samples": [
            {
              "provider": "seed",
              "value": 7200000000
            },
            {
              "provider": "coingecko",
              "value": 1776793510
            }
          ]
        },
        {
          "field": "est_liquidity_usd",
          "type": "numeric_divergence",
          "divergence_ratio": 12672.286,
          "samples": [
            {
              "provider": "seed",
              "value": 220000000
            },
            {
              "provider": "coingecko",
              "value": 17359.35
            }
          ]
        }
      ]
    },
    {
      "asset_id": "sei",
      "name": "Sei",
      "symbol": "SEI",
      "origin_chain": "Sei",
      "rejection_reasons": [
        "insufficient_estimated_liquidity"
      ],
      "data_conflicts": [
        {
          "field": "mcap_usd",
          "type": "numeric_divergence",
          "divergence_ratio": 4.761,
          "samples": [
            {
              "provider": "seed",
              "value": 2200000000
            },
            {
              "provider": "coingecko",
              "value": 381902328
            }
          ]
        },
        {
          "field": "fdv_usd",
          "type": "numeric_divergence",
          "divergence_ratio": 7.463,
          "samples": [
            {
              "provider": "seed",
              "value": 4800000000
            },
            {
              "provider": "coingecko",
              "value": 567181675
            }
          ]
        },
        {
          "field": "est_liquidity_usd",
          "type": "numeric_divergence",
          "divergence_ratio": 14.031,
          "samples": [
            {
              "provider": "seed",
              "value": 80000000
            },
            {
              "provider": "coingecko",
              "value": 5322177.149999999
            }
          ]
        }
      ]
    },
    {
      "asset_id": "injective",
      "name": "Injective",
      "symbol": "INJ",
      "origin_chain": "Injective",
      "rejection_reasons": [
        "insufficient_estimated_liquidity"
      ],
      "data_conflicts": [
        {
          "field": "mcap_usd",
          "type": "numeric_divergence",
          "divergence_ratio": 7.214,
          "samples": [
            {
              "provider": "seed",
              "value": 2700000000
            },
            {
              "provider": "coingecko",
              "value": 328691231
            }
          ]
        },
        {
          "field": "fdv_usd",
          "type": "numeric_divergence",
          "divergence_ratio": 7.519,
          "samples": [
            {
              "provider": "seed",
              "value": 2800000000
            },
            {
              "provider": "coingecko",
              "value": 328691231
            }
          ]
        },
        {
          "field": "est_liquidity_usd",
          "type": "numeric_divergence",
          "divergence_ratio": 12.671,
          "samples": [
            {
              "provider": "seed",
              "value": 90000000
            },
            {
              "provider": "coingecko",
              "value": 6583173.45
            }
          ]
        }
      ]
    },
    {
      "asset_id": "wormhole",
      "name": "Wormhole",
      "symbol": "W",
      "origin_chain": "Solana",
      "rejection_reasons": [
        "insufficient_estimated_liquidity"
      ],
      "data_conflicts": [
        {
          "field": "mcap_usd",
          "type": "numeric_divergence",
          "divergence_ratio": 20.88,
          "samples": [
            {
              "provider": "seed",
              "value": 1600000000
            },
            {
              "provider": "coingecko",
              "value": 73126072
            }
          ]
        },
        {
          "field": "fdv_usd",
          "type": "numeric_divergence",
          "divergence_ratio": 44.508,
          "samples": [
            {
              "provider": "seed",
              "value": 5800000000
            },
            {
              "provider": "coingecko",
              "value": 127451115
            }
          ]
        },
        {
          "field": "est_liquidity_usd",
          "type": "numeric_divergence",
          "divergence_ratio": 21.724,
          "samples": [
            {
              "provider": "seed",
              "value": 75000000
            },
            {
              "provider": "coingecko",
              "value": 3300465.15
            }
          ]
        }
      ]
    },
    {
      "asset_id": "jupiter",
      "name": "Jupiter",
      "symbol": "JUP",
      "origin_chain": "Solana",
      "rejection_reasons": [
        "insufficient_estimated_liquidity"
      ],
      "data_conflicts": [
        {
          "field": "mcap_usd",
          "type": "numeric_divergence",
          "divergence_ratio": 2.123,
          "samples": [
            {
              "provider": "seed",
              "value": 2000000000
            },
            {
              "provider": "coingecko",
              "value": 640481939
            }
          ]
        },
        {
          "field": "fdv_usd",
          "type": "numeric_divergence",
          "divergence_ratio": 4.573,
          "samples": [
            {
              "provider": "seed",
              "value": 6900000000
            },
            {
              "provider": "coingecko",
              "value": 1238090700
            }
          ]
        },
        {
          "field": "est_liquidity_usd",
          "type": "numeric_divergence",
          "divergence_ratio": 29.389,
          "samples": [
            {
              "provider": "seed",
              "value": 110000000
            },
            {
              "provider": "coingecko",
              "value": 3619671.75
            }
          ]
        }
      ]
    },
    {
      "asset_id": "dogecoin",
      "name": "Dogecoin",
      "symbol": "DOGE",
      "origin_chain": "Dogecoin",
      "rejection_reasons": [
        "unsupported_origin_chain"
      ],
      "data_conflicts": [
        {
          "field": "mcap_usd",
          "type": "numeric_divergence",
          "divergence_ratio": 0.557,
          "samples": [
            {
              "provider": "seed",
              "value": 23000000000
            },
            {
              "provider": "coingecko",
              "value": 14771905897
            }
          ]
        },
        {
          "field": "fdv_usd",
          "type": "numeric_divergence",
          "divergence_ratio": 0.413,
          "samples": [
            {
              "provider": "seed",
              "value": 23000000000
            },
            {
              "provider": "coingecko",
              "value": 16280152280
            }
          ]
        },
        {
          "field": "est_liquidity_usd",
          "type": "numeric_divergence",
          "divergence_ratio": 1.106,
          "samples": [
            {
              "provider": "seed",
              "value": 550000000
            },
            {
              "provider": "coingecko",
              "value": 261139633.79999998
            }
          ]
        }
      ]
    },
    {
      "asset_id": "eigenlayer",
      "name": "EigenLayer",
      "symbol": "EIGEN",
      "origin_chain": "Ethereum",
      "rejection_reasons": [
        "insufficient_estimated_liquidity"
      ],
      "data_conflicts": [
        {
          "field": "mcap_usd",
          "type": "numeric_divergence",
          "divergence_ratio": 2.248,
          "samples": [
            {
              "provider": "seed",
              "value": 420000000
            },
            {
              "provider": "coingecko",
              "value": 129312048
            }
          ]
        },
        {
          "field": "fdv_usd",
          "type": "numeric_divergence",
          "divergence_ratio": 7.557,
          "samples": [
            {
              "provider": "seed",
              "value": 2900000000
            },
            {
              "provider": "coingecko",
              "value": 338891063
            }
          ]
        },
        {
          "field": "est_liquidity_usd",
          "type": "numeric_divergence",
          "divergence_ratio": 2.389,
          "samples": [
            {
              "provider": "seed",
              "value": 14000000
            },
            {
              "provider": "coingecko",
              "value": 4131475.1999999997
            }
          ]
        }
      ]
    },
    {
      "asset_id": "lido-dao",
      "name": "Lido DAO",
      "symbol": "LDO",
      "origin_chain": "Ethereum",
      "rejection_reasons": [
        "insufficient_estimated_liquidity"
      ],
      "data_conflicts": [
        {
          "field": "mcap_usd",
          "type": "numeric_divergence",
          "divergence_ratio": 4.253,
          "samples": [
            {
              "provider": "seed",
              "value": 1800000000
            },
            {
              "provider": "coingecko",
              "value": 342629599
            }
          ]
        },
        {
          "field": "fdv_usd",
          "type": "numeric_divergence",
          "divergence_ratio": 3.709,
          "samples": [
            {
              "provider": "seed",
              "value": 1900000000
            },
            {
              "provider": "coingecko",
              "value": 403478062
            }
          ]
        },
        {
          "field": "est_liquidity_usd",
          "type": "numeric_divergence",
          "divergence_ratio": 11.158,
          "samples": [
            {
              "provider": "seed",
              "value": 67000000
            },
            {
              "provider": "coingecko",
              "value": 5510862.149999999
            }
          ]
        }
      ]
    },
    {
      "asset_id": "brett",
      "name": "Brett",
      "symbol": "BRETT",
      "origin_chain": "Base",
      "rejection_reasons": [
        "no_tier1_cex_listing",
        "below_min_tier1_cex_count",
        "insufficient_estimated_liquidity"
      ],
      "data_conflicts": [
        {
          "field": "mcap_usd",
          "type": "numeric_divergence",
          "divergence_ratio": 7.234,
          "samples": [
            {
              "provider": "seed",
              "value": 600000000
            },
            {
              "provider": "coingecko",
              "value": 72866356
            }
          ]
        },
        {
          "field": "fdv_usd",
          "type": "numeric_divergence",
          "divergence_ratio": 7.234,
          "samples": [
            {
              "provider": "seed",
              "value": 600000000
            },
            {
              "provider": "coingecko",
              "value": 72866356
            }
          ]
        },
        {
          "field": "est_liquidity_usd",
          "type": "numeric_divergence",
          "divergence_ratio": 3.338,
          "samples": [
            {
              "provider": "seed",
              "value": 6000000
            },
            {
              "provider": "coingecko",
              "value": 1383011.0999999999
            }
          ]
        }
      ]
    },
    {
      "asset_id": "kaspa",
      "name": "Kaspa",
      "symbol": "KAS",
      "origin_chain": "Kaspa",
      "rejection_reasons": [
        "unsupported_origin_chain",
        "insufficient_estimated_liquidity"
      ],
      "data_conflicts": [
        {
          "field": "mcap_usd",
          "type": "numeric_divergence",
          "divergence_ratio": 3.015,
          "samples": [
            {
              "provider": "seed",
              "value": 3800000000
            },
            {
              "provider": "coingecko",
              "value": 946550993
            }
          ]
        },
        {
          "field": "fdv_usd",
          "type": "numeric_divergence",
          "divergence_ratio": 3.008,
          "samples": [
            {
              "provider": "seed",
              "value": 3800000000
            },
            {
              "provider": "coingecko",
              "value": 948113913
            }
          ]
        },
        {
          "field": "est_liquidity_usd",
          "type": "numeric_divergence",
          "divergence_ratio": 27.707,
          "samples": [
            {
              "provider": "seed",
              "value": 120000000
            },
            {
              "provider": "coingecko",
              "value": 4180096.3499999996
            }
          ]
        }
      ]
    }
  ],
  "launch_briefs": [
    {
      "asset_id": "chainlink",
      "asset_name": "Chainlink",
      "symbol": "LINK",
      "origin_chain": "Ethereum",
      "eligibility": {
        "eligible": true,
        "gate_status": "pass",
        "rejection_reasons": [],
        "borderline_reasons": []
      },
      "readiness_score": 70.06,
      "adjusted_readiness_score": 66.44,
      "confidence_score": 74.18,
      "selected_for": [
        "Strong market profile (MCAP: $6,839,634,847, FDV: $9,406,732,396)",
        "Tier-1 CEX footprint (OKX, Bybit, Binance, Kraken)",
        "Estimated deployable liquidity: $52,342,134",
        "Solana demand signal score: 85/100"
      ],
      "risks": [
        "No critical risks flagged in v1 rule set."
      ],
      "assumptions": [
        "Market and liquidity metrics are time-sensitive and require refresh pre-submission.",
        "Tier-1 CEX list follows v1 default and may change with sponsor feedback."
      ],
      "next_actions": [
        "Validate canonical route and token representation with Sunrise.",
        "Confirm launch-day liquidity commitments and venue sequencing.",
        "Validate demand channels across Solana protocols and ecosystem partners."
      ],
      "source_notes": "Seeded from public market references; refresh with live API before final submission."
    },
    {
      "asset_id": "sui",
      "asset_name": "Sui",
      "symbol": "SUI",
      "origin_chain": "Sui",
      "eligibility": {
        "eligible": true,
        "gate_status": "pass",
        "rejection_reasons": [],
        "borderline_reasons": []
      },
      "readiness_score": 70.13,
      "adjusted_readiness_score": 66.39,
      "confidence_score": 73.35,
      "selected_for": [
        "Strong market profile (MCAP: $3,823,625,333, FDV: $9,671,766,169)",
        "Tier-1 CEX footprint (Binance, Coinbase, OKX, Bybit, Kraken)",
        "Estimated deployable liquidity: $62,030,213.25",
        "Solana demand signal score: 81.4/100"
      ],
      "risks": [
        "Data quality gaps: missing_origin_token_address"
      ],
      "assumptions": [
        "Market and liquidity metrics are time-sensitive and require refresh pre-submission.",
        "Tier-1 CEX list follows v1 default and may change with sponsor feedback."
      ],
      "next_actions": [
        "Validate canonical route and token representation with Sunrise.",
        "Confirm launch-day liquidity commitments and venue sequencing.",
        "Validate demand channels across Solana protocols and ecosystem partners."
      ],
      "source_notes": "Seeded estimate."
    },
    {
      "asset_id": "avalanche",
      "asset_name": "Avalanche",
      "symbol": "AVAX",
      "origin_chain": "Avalanche",
      "eligibility": {
        "eligible": true,
        "gate_status": "pass",
        "rejection_reasons": [],
        "borderline_reasons": []
      },
      "readiness_score": 67.98,
      "adjusted_readiness_score": 63.79,
      "confidence_score": 69.22,
      "selected_for": [
        "Strong market profile (MCAP: $4,069,677,724, FDV: $4,368,175,641)",
        "Tier-1 CEX footprint (Binance, Coinbase, OKX, Bybit, Kraken)",
        "Estimated deployable liquidity: $43,290,970.8",
        "Solana demand signal score: 80.6/100"
      ],
      "risks": [
        "Data quality gaps: missing_origin_token_address"
      ],
      "assumptions": [
        "Market and liquidity metrics are time-sensitive and require refresh pre-submission.",
        "Tier-1 CEX list follows v1 default and may change with sponsor feedback."
      ],
      "next_actions": [
        "Validate canonical route and token representation with Sunrise.",
        "Confirm launch-day liquidity commitments and venue sequencing.",
        "Validate demand channels across Solana protocols and ecosystem partners."
      ],
      "source_notes": "Seeded estimate."
    },
    {
      "asset_id": "pepe",
      "asset_name": "Pepe",
      "symbol": "PEPE",
      "origin_chain": "Ethereum",
      "eligibility": {
        "eligible": true,
        "gate_status": "pass",
        "rejection_reasons": [],
        "borderline_reasons": []
      },
      "readiness_score": 63.75,
      "adjusted_readiness_score": 60.33,
      "confidence_score": 73.18,
      "selected_for": [
        "Strong market profile (MCAP: $1,605,497,385, FDV: $1,605,497,385)",
        "Tier-1 CEX footprint (Binance, Coinbase, OKX, Bybit, Kraken)",
        "Estimated deployable liquidity: $62,000,985.6",
        "Solana demand signal score: 84.9/100"
      ],
      "risks": [
        "No critical risks flagged in v1 rule set."
      ],
      "assumptions": [
        "Market and liquidity metrics are time-sensitive and require refresh pre-submission.",
        "Tier-1 CEX list follows v1 default and may change with sponsor feedback."
      ],
      "next_actions": [
        "Validate canonical route and token representation with Sunrise.",
        "Confirm launch-day liquidity commitments and venue sequencing.",
        "Validate demand channels across Solana protocols and ecosystem partners."
      ],
      "source_notes": "Seeded estimate."
    },
    {
      "asset_id": "uniswap",
      "asset_name": "Uniswap",
      "symbol": "UNI",
      "origin_chain": "Ethereum",
      "eligibility": {
        "eligible": true,
        "gate_status": "pass",
        "rejection_reasons": [],
        "borderline_reasons": []
      },
      "readiness_score": 61.64,
      "adjusted_readiness_score": 58.37,
      "confidence_score": 73.44,
      "selected_for": [
        "Strong market profile (MCAP: $2,148,020,951, FDV: $3,040,421,843)",
        "Tier-1 CEX footprint (Binance, OKX, Bybit, Kraken)",
        "Estimated deployable liquidity: $27,924,208.2",
        "Solana demand signal score: 81.6/100"
      ],
      "risks": [
        "No critical risks flagged in v1 rule set."
      ],
      "assumptions": [
        "Market and liquidity metrics are time-sensitive and require refresh pre-submission.",
        "Tier-1 CEX list follows v1 default and may change with sponsor feedback."
      ],
      "next_actions": [
        "Validate canonical route and token representation with Sunrise.",
        "Confirm launch-day liquidity commitments and venue sequencing.",
        "Validate demand channels across Solana protocols and ecosystem partners."
      ],
      "source_notes": "Seeded estimate."
    }
  ],
  "validation_errors": []
}
